evilworm/__init__.py
evilwormgpt-0.2.dist-info/METADATA
evilwormgpt-0.2.dist-info/WHEEL
evilwormgpt-0.2.dist-info/top_level.txt
evilwormgpt-0.2.dist-info/RECORD
