Metadata-Version: 2.4
Name: evilwormgpt
Version: 0.2
Summary: Unofficial wrapper for a sarcastic and evil GPT-style API chatbot
Home-page: https://github.com/hamza/evilwormgpt
Author: Hamza
Author-email: hamza@example.com
Classifier: Programming Language :: Python :: 3
Classifier: Operating System :: OS Independent
Classifier: Intended Audience :: Developers
Classifier: Topic :: Communications :: Chat
Classifier: License :: OSI Approved :: MIT License
Requires-Python: >=3.6
Requires-Dist: requests
Dynamic: author
Dynamic: author-email
Dynamic: classifier
Dynamic: description
Dynamic: description-content-type
Dynamic: home-page
Dynamic: requires-dist
Dynamic: requires-python
Dynamic: summary
